{
  "configurations": {
    "config_enterprise_application_1640995200": {
      "config_id": "config_enterprise_application_1640995200",
      "config_name": "enterprise_application",
      "scope": "application",
      "data": {
        "application": {
          "name": "MIA Enterprise AGI",
          "version": "1.0.0",
          "environment": "production"
        },
        "database": {
          "type": "postgresql",
          "host": "localhost",
          "port": 5432,
          "pool_size": 10
        },
        "security": {
          "encryption_enabled": true,
          "audit_logging": true,
          "access_control": true
        },
        "logging": {
          "level": "INFO",
          "format": "json",
          "rotation": "daily"
        },
        "performance": {
          "cache_enabled": true,
          "optimization": "balanced"
        }
      },
      "created_at": "2025-12-09T13:14:34.323502",
      "created_by": "system",
      "version": "1.0",
      "status": "active",
      "metadata": {
        "description": "",
        "tags": [],
        "environment": "production"
      }
    },
    "config_enterprise_security_1640995200": {
      "config_id": "config_enterprise_security_1640995200",
      "config_name": "enterprise_security",
      "scope": "application",
      "data": {
        "security": {
          "authentication": {
            "method": "multi_factor",
            "session_timeout": 3600,
            "password_policy": "strong"
          },
          "authorization": {
            "rbac_enabled": true,
            "default_role": "user",
            "admin_approval_required": true
          },
          "encryption": {
            "algorithm": "AES-256",
            "key_rotation": "monthly",
            "at_rest": true,
            "in_transit": true
          }
        }
      },
      "created_at": "2025-12-09T13:14:34.323766",
      "created_by": "system",
      "version": "1.0",
      "status": "active",
      "metadata": {
        "description": "",
        "tags": [],
        "environment": "production"
      }
    }
  },
  "configuration_history": [
    {
      "action": "configuration_created",
      "config_id": "config_enterprise_application_1640995200",
      "config_name": "enterprise_application",
      "timestamp": "2025-12-09T13:14:34.323507",
      "details": {
        "config_id": "config_enterprise_application_1640995200",
        "config_name": "enterprise_application",
        "scope": "application",
        "data": {
          "application": {
            "name": "MIA Enterprise AGI",
            "version": "1.0.0",
            "environment": "production"
          },
          "database": {
            "type": "postgresql",
            "host": "localhost",
            "port": 5432,
            "pool_size": 10
          },
          "security": {
            "encryption_enabled": true,
            "audit_logging": true,
            "access_control": true
          },
          "logging": {
            "level": "INFO",
            "format": "json",
            "rotation": "daily"
          },
          "performance": {
            "cache_enabled": true,
            "optimization": "balanced"
          }
        },
        "created_at": "2025-12-09T13:14:34.323502",
        "created_by": "system",
        "version": "1.0",
        "status": "active",
        "metadata": {
          "description": "",
          "tags": [],
          "environment": "production"
        }
      }
    },
    {
      "action": "configuration_created",
      "config_id": "config_enterprise_security_1640995200",
      "config_name": "enterprise_security",
      "timestamp": "2025-12-09T13:14:34.323772",
      "details": {
        "config_id": "config_enterprise_security_1640995200",
        "config_name": "enterprise_security",
        "scope": "application",
        "data": {
          "security": {
            "authentication": {
              "method": "multi_factor",
              "session_timeout": 3600,
              "password_policy": "strong"
            },
            "authorization": {
              "rbac_enabled": true,
              "default_role": "user",
              "admin_approval_required": true
            },
            "encryption": {
              "algorithm": "AES-256",
              "key_rotation": "monthly",
              "at_rest": true,
              "in_transit": true
            }
          }
        },
        "created_at": "2025-12-09T13:14:34.323766",
        "created_by": "system",
        "version": "1.0",
        "status": "active",
        "metadata": {
          "description": "",
          "tags": [],
          "environment": "production"
        }
      }
    }
  ],
  "configuration_templates": {},
  "config": {
    "centralized_management": true,
    "configuration_validation": true,
    "change_tracking": true,
    "backup_configurations": true,
    "encryption_enabled": true
  },
  "last_updated": "2025-12-09T13:14:34.323820"
}